Simplate/Simplate.py
Simplate/__init__.py
Simplate-1.0.2.dist-info/LICENSE
Simplate-1.0.2.dist-info/METADATA
Simplate-1.0.2.dist-info/WHEEL
Simplate-1.0.2.dist-info/top_level.txt
Simplate-1.0.2.dist-info/RECORD
