Metadata-Version: 2.1
Name: Simplate
Version: 1.0.2
Summary: Simple object-based string templating in python
Home-page: https://github.com/krkimery/simplate
Author: Kyle Kimery
Author-email: kylekimery@gmail.com
License: UNKNOWN
Platform: UNKNOWN
Classifier: Programming Language :: Python :: 2.7
Classifier: License :: OSI Approved :: MIT License
Classifier: Operating System :: OS Independent
